README.rst
setup.cfg
setup.py
django_drf_file_generator.egg-info/PKG-INFO
django_drf_file_generator.egg-info/SOURCES.txt
django_drf_file_generator.egg-info/dependency_links.txt
django_drf_file_generator.egg-info/entry_points.txt
django_drf_file_generator.egg-info/not-zip-safe
django_drf_file_generator.egg-info/top_level.txt
drf_gen/__init__.py
drf_gen/config.ini
drf_gen/config.py
drf_gen/drf_gen.py