Metadata-Version: 1.1
Name: django-drf-file-generator
Version: 0.1.15
Summary: Django DRF File Generator provides a safe way to generate automatically Django basic files like url.py, serializers.py, admin.py, views.py, to use with djangorestframework, the genereted files are based on your models.py
Home-page: https://github.com/AlexandreProenca/django-drf-file-generator
Author: Alexandre Proença
Author-email: alexandre.proenca@hotmail.com.br
License: MIT
Keywords: django
Platform: UNKNOWN
Classifier: Development Status :: 2 - Pre-Alpha
Classifier: Environment :: Web Environment
Classifier: Framework :: Django
Classifier: Intended Audience :: Developers
Classifier: License :: OSI Approved :: MIT License
Classifier: Operating System :: OS Independent
Classifier: Programming Language :: Python
Classifier: Programming Language :: Python :: 3
Classifier: Topic :: Internet :: WWW/HTTP
